<?xml version="1.0" encoding="UTF-8"?><record_update table="sp_header_footer">
    <sp_header_footer action="DELETE">
        <category>standard</category>
        <client_script><![CDATA[		]]></client_script>
        <controller_as>c</controller_as>
        <css>.navbar {
  transition: 250ms opacity ease-in-out;
  -webkit-transition: 250ms opacity ease-in-out;
  border: 0;
  border-bottom: 4px solid $sp-navbar-divider-color;
}

.navbar-fade {
  opacity: 0.4;
}

.navbar-inverse .navbar-toggle {
  border-color: rgba(255, 255, 255, 0.25);
}

header[role="banner"],
.nav &gt; li &gt; a {
  max-height: 60px;
}

.nav &gt; li &gt; a span.fa{
  margin-left: 0.2rem;
}

@media screen and (max-width: 992px){
  .nav &gt; li &gt; a {
    padding-right: 0.5rem;
    padding-left: 0.5rem;
  }
}

.navbar-brand {
  max-height: 60px;
  padding: 0;
  padding-bottom: 0.5rem;
}

.navbar-brand img, .navbar-brand span {
  margin-left: $sp-logo-margin-x;
  margin-right: $sp-logo-margin-x;
  margin-top: $sp-logo-margin-y;
  margin-bottom: $sp-logo-margin-y;
  display: block;
  max-height: $sp-logo-max-height;
  max-width: $sp-logo-max-width;
  position: relative;
  top: 150%;
  -webkit-transform: translateY(-50%);
  -ms-transform: translateY(-50%);
  transform: translateY(-50%);
  overflow: hidden;
}

@media screen and (max-width: 992px){
  .navbar-brand img, .navbar-brand span {
    max-width: $sp-logo-mobile-max-width;
  }
}

.breadcrumb-container {
  background-color: $panel-bg;
}

/* for mobile app */
.navbar-inverse.is-native {
  background-color: #405060;
}

nav {
  margin-bottom: 0px;
  border-radius: 0px;

 .toggle-dropdown {
    height: 60px;
  }

}

.navbar-right {
  padding-right: 0px;
  padding-left: 7px;
}

.navbar-nav {
margin: 0px;
}

// PRB711244: Dropdown menu is scrollable when too many items
.scrollable-dropdown {
  max-height: 80vh;
  overflow: auto;
  height: auto;
}

.is-native {
 .scrollable-dropdown {
  max-height: 100vh;
  overflow: scroll;
  height: auto;
	}
}


/* PRB923910: Fix for Service Portal - Header Poorly Aligned in Safari */
@media screen and (min-width: 993px) {
  .navbar-right {
    display: flex !important;
    height: auto !important;
  }
}

@media (max-width: 992px) {
  .navbar-toggle {
    display: block;
  }
  .navbar-header {
    float: none;
  }
  .navbar-left,.navbar-right {
    float: none !important;
  }
  .navbar-nav {
    float: none !important;
  }
  .navbar-nav &gt; li {
    float: none;
  }
  .navbar-nav &gt; li &gt; a {
    padding-top: 1rem ;
    padding-bottom: 1rem;
  }
}</css>
        <data_table>sp_instance</data_table>
        <demo_data/>
        <description/>
        <docs/>
        <field_list/>
        <has_preview>true</has_preview>
        <id/>
        <internal>false</internal>
        <link/>
        <name>Auctionarc_header</name>
        <option_schema/>
        <public>true</public>
        <roles/>
        <script/>
        <servicenow>false</servicenow>
        <static>false</static>
        <sys_class_name>sp_header_footer</sys_class_name>
        <sys_created_by>CC-Supradhar</sys_created_by>
        <sys_created_on>2023-05-09 06:15:59</sys_created_on>
        <sys_id>3dd1d8041b3661109cb1639bbc4bcb36</sys_id>
        <sys_mod_count>13</sys_mod_count>
        <sys_name>Auctionarc_header</sys_name>
        <sys_package display_value="AuctionArc" source="x_1046400_auction">6e876ac81b2ae1109cb1639bbc4bcb2b</sys_package>
        <sys_policy/>
        <sys_scope display_value="AuctionArc">6e876ac81b2ae1109cb1639bbc4bcb2b</sys_scope>
        <sys_update_name>sp_header_footer_3dd1d8041b3661109cb1639bbc4bcb36</sys_update_name>
        <sys_updated_by>CC-Harsha</sys_updated_by>
        <sys_updated_on>2023-05-11 09:26:45</sys_updated_on>
        <template><![CDATA[

<div>
  <nav class="navbar-inverse" ng-class="::{'navbar':!isViewNative, 'is-native': isViewNative}"
       role="navigation" aria-label="${Primary}">
    <div ng-show="::!isViewNative" class="navbar-header">
<a class="navbar-brand" ng-if="::!portal.logo" href="?id={{::portal.homepage_dv}}"><span ng-bind="portal.title"></span></a>
      <a class="navbar-brand navbar-brand-logo" ng-if="::portal.logo" ng-href="?id={{::portal.homepage_dv}}" ng-click="collapse()" aria-label="{{::logoText}}">
        <img ng-src="{{::portal.logo}}" title="{{::portal.title}}" role="presentation" alt="{{::portal.title}} ${Logo}" />
      </a>
      <button ng-if="data.hasMenuItems || (!user.logged_in && page.id != portal.login_page_dv && !data.hasLogin) || user.logged_in" type="button" class="navbar-toggle collapsed" data-toggle="collapse" data-target="#sp-nav-bar" aria-haspopup="menu">
        <span class="sr-only">${Toggle navigation}</span>
        <span class="icon-bar"></span>
        <span class="icon-bar"></span>
        <span class="icon-bar"></span>
      </button>
    </div>

    <div sp-navbar-toggle="" class="collapse navbar-right" id="sp-nav-bar">
      <!-- Include The Menu -->
      <sp-widget widget="::data.menu"></sp-widget>
	  <!-- Language Selector Menu -->
      <sp-widget widget="::data.langSelector"></sp-widget>
      <ul ng-if="(!user.logged_in && page.id != portal.login_page_dv && !data.hasLogin)" class="nav navbar-nav" role="presentation">
        <li role="presentation"><a href ng-click="::openLogin()">${Login}</a></li>
      </ul>
      <ul ng-if="user.logged_in" class="nav navbar-nav" role="menubar">
        <!-- chat, avatar, and logout -->
        <li ng-if="::(data.connect_support_queue_id && !isAgentChatConfigured)" role="presentation"><a href ng-click="openPopUp()" role="menuitem">${Live Chat}</a></li>
        <li ng-if="showAvatar" class="hidden-xs hidden-sm dropdown" role="presentation">
          <a href class="toggle-dropdown" data-toggle="dropdown" aria-expanded="false" aria-label="{{::data.profileBtnMsg}}: {{::user.name}}" id="profile-dropdown"  role="menuitem" aria-haspopup="true">
            <span class="navbar-avatar" aria-hidden="true"><sn-avatar class="avatar-small-medium" primary="avatarProfile" /></span>
            <span class="visible-lg-inline">{{::user.name}}</span>
          </a>
          <ul class="dropdown-menu" role="menu" aria-label="{{::data.profileBtnMsg}}">
            <li role="presentation"><a tabindex="-1" ng-href="?id=user_profile&sys_id={{::user.sys_id}}" role="menuitem">${Profile}</a></li>
            <li ng-if="::!(isViewNative || isViewNativeTablet)" role="presentation"><a tabindex="-1" href="{{::portal.logoutUrl}}" role="menuitem">${Logout}</a></li>
          </ul>
        </li>
        <li ng-if="showSMAvatar" class="visible-xs-block visible-sm-block" role="presentation"><a role="menuitem" ng-href="?id=user_profile&sys_id={{::user.sys_id}}" ng-click="collapse()">
          <span class="navbar-avatar"><sn-avatar class="avatar-small-medium" primary="avatarProfile" /></span>{{::user.name}}</a>
        </li>
        <li ng-if="::!(isViewNative || isViewNativeTablet)" class="visible-xs-block visible-sm-block" role="presentation"><a role="menuitem" ng-href="{{::portal.logoutUrl}}" ng-click="collapse()">${Logout}</a></li>
      </ul>
    </div>
  </nav>
</div>]]></template>
    </sp_header_footer>
    <sys_update_version action="INSERT_OR_UPDATE">
        <action>DELETE</action>
        <application display_value="AuctionArc">6e876ac81b2ae1109cb1639bbc4bcb2b</application>
        <file_path/>
        <instance_id>c036af0fdb0613000e785d00cf9619a3</instance_id>
        <instance_name>dev59662</instance_name>
        <name>sp_header_footer_3dd1d8041b3661109cb1639bbc4bcb36</name>
        <payload>&lt;?xml version="1.0" encoding="UTF-8"?&gt;&lt;record_update table="sp_header_footer"&gt;&lt;sp_header_footer action="INSERT_OR_UPDATE"&gt;&lt;category&gt;standard&lt;/category&gt;&lt;client_script&gt;&lt;![CDATA[		]]&gt;&lt;/client_script&gt;&lt;controller_as&gt;c&lt;/controller_as&gt;&lt;css&gt;.navbar {
  transition: 250ms opacity ease-in-out;
  -webkit-transition: 250ms opacity ease-in-out;
  border: 0;
  border-bottom: 4px solid $sp-navbar-divider-color;
}

.navbar-fade {
  opacity: 0.4;
}

.navbar-inverse .navbar-toggle {
  border-color: rgba(255, 255, 255, 0.25);
}

header[role="banner"],
.nav &amp;gt; li &amp;gt; a {
  max-height: 60px;
}

.nav &amp;gt; li &amp;gt; a span.fa{
  margin-left: 0.2rem;
}

@media screen and (max-width: 992px){
  .nav &amp;gt; li &amp;gt; a {
    padding-right: 0.5rem;
    padding-left: 0.5rem;
  }
}

.navbar-brand {
  max-height: 60px;
  padding: 0;
  padding-bottom: 0.5rem;
}

.navbar-brand img, .navbar-brand span {
  margin-left: $sp-logo-margin-x;
  margin-right: $sp-logo-margin-x;
  margin-top: $sp-logo-margin-y;
  margin-bottom: $sp-logo-margin-y;
  display: block;
  max-height: $sp-logo-max-height;
  max-width: $sp-logo-max-width;
  position: relative;
  top: 150%;
  -webkit-transform: translateY(-50%);
  -ms-transform: translateY(-50%);
  transform: translateY(-50%);
  overflow: hidden;
}

@media screen and (max-width: 992px){
  .navbar-brand img, .navbar-brand span {
    max-width: $sp-logo-mobile-max-width;
  }
}

.breadcrumb-container {
  background-color: $panel-bg;
}

/* for mobile app */
.navbar-inverse.is-native {
  background-color: #405060;
}

nav {
  margin-bottom: 0px;
  border-radius: 0px;

 .toggle-dropdown {
    height: 60px;
  }

}

.navbar-right {
  padding-right: 0px;
  padding-left: 7px;
}

.navbar-nav {
margin: 0px;
}

// PRB711244: Dropdown menu is scrollable when too many items
.scrollable-dropdown {
  max-height: 80vh;
  overflow: auto;
  height: auto;
}

.is-native {
 .scrollable-dropdown {
  max-height: 100vh;
  overflow: scroll;
  height: auto;
	}
}


/* PRB923910: Fix for Service Portal - Header Poorly Aligned in Safari */
@media screen and (min-width: 993px) {
  .navbar-right {
    display: flex !important;
    height: auto !important;
  }
}

@media (max-width: 992px) {
  .navbar-toggle {
    display: block;
  }
  .navbar-header {
    float: none;
  }
  .navbar-left,.navbar-right {
    float: none !important;
  }
  .navbar-nav {
    float: none !important;
  }
  .navbar-nav &amp;gt; li {
    float: none;
  }
  .navbar-nav &amp;gt; li &amp;gt; a {
    padding-top: 1rem ;
    padding-bottom: 1rem;
  }
}&lt;/css&gt;&lt;data_table&gt;sp_instance&lt;/data_table&gt;&lt;demo_data/&gt;&lt;description/&gt;&lt;docs/&gt;&lt;field_list/&gt;&lt;has_preview&gt;true&lt;/has_preview&gt;&lt;id/&gt;&lt;internal&gt;false&lt;/internal&gt;&lt;link/&gt;&lt;name&gt;Auctionarc_header&lt;/name&gt;&lt;option_schema/&gt;&lt;public&gt;true&lt;/public&gt;&lt;roles/&gt;&lt;script/&gt;&lt;servicenow&gt;false&lt;/servicenow&gt;&lt;static&gt;false&lt;/static&gt;&lt;sys_class_name&gt;sp_header_footer&lt;/sys_class_name&gt;&lt;sys_created_by&gt;CC-Supradhar&lt;/sys_created_by&gt;&lt;sys_created_on&gt;2023-05-09 06:15:59&lt;/sys_created_on&gt;&lt;sys_id&gt;3dd1d8041b3661109cb1639bbc4bcb36&lt;/sys_id&gt;&lt;sys_mod_count&gt;13&lt;/sys_mod_count&gt;&lt;sys_name&gt;Auctionarc_header&lt;/sys_name&gt;&lt;sys_package display_value="AuctionArc" source="x_1046400_auction"&gt;6e876ac81b2ae1109cb1639bbc4bcb2b&lt;/sys_package&gt;&lt;sys_policy/&gt;&lt;sys_scope display_value="AuctionArc"&gt;6e876ac81b2ae1109cb1639bbc4bcb2b&lt;/sys_scope&gt;&lt;sys_update_name&gt;sp_header_footer_3dd1d8041b3661109cb1639bbc4bcb36&lt;/sys_update_name&gt;&lt;sys_updated_by&gt;CC-Harsha&lt;/sys_updated_by&gt;&lt;sys_updated_on&gt;2023-05-11 09:26:45&lt;/sys_updated_on&gt;&lt;template&gt;&lt;![CDATA[

&lt;div&gt;
  &lt;nav class="navbar-inverse" ng-class="::{'navbar':!isViewNative, 'is-native': isViewNative}"
       role="navigation" aria-label="${Primary}"&gt;
    &lt;div ng-show="::!isViewNative" class="navbar-header"&gt;
&lt;a class="navbar-brand" ng-if="::!portal.logo" href="?id={{::portal.homepage_dv}}"&gt;&lt;span ng-bind="portal.title"&gt;&lt;/span&gt;&lt;/a&gt;
      &lt;a class="navbar-brand navbar-brand-logo" ng-if="::portal.logo" ng-href="?id={{::portal.homepage_dv}}" ng-click="collapse()" aria-label="{{::logoText}}"&gt;
        &lt;img ng-src="{{::portal.logo}}" title="{{::portal.title}}" role="presentation" alt="{{::portal.title}} ${Logo}" /&gt;
      &lt;/a&gt;
      &lt;button ng-if="data.hasMenuItems || (!user.logged_in &amp;&amp; page.id != portal.login_page_dv &amp;&amp; !data.hasLogin) || user.logged_in" type="button" class="navbar-toggle collapsed" data-toggle="collapse" data-target="#sp-nav-bar" aria-haspopup="menu"&gt;
        &lt;span class="sr-only"&gt;${Toggle navigation}&lt;/span&gt;
        &lt;span class="icon-bar"&gt;&lt;/span&gt;
        &lt;span class="icon-bar"&gt;&lt;/span&gt;
        &lt;span class="icon-bar"&gt;&lt;/span&gt;
      &lt;/button&gt;
    &lt;/div&gt;

    &lt;div sp-navbar-toggle="" class="collapse navbar-right" id="sp-nav-bar"&gt;
      &lt;!-- Include The Menu --&gt;
      &lt;sp-widget widget="::data.menu"&gt;&lt;/sp-widget&gt;
	  &lt;!-- Language Selector Menu --&gt;
      &lt;sp-widget widget="::data.langSelector"&gt;&lt;/sp-widget&gt;
      &lt;ul ng-if="(!user.logged_in &amp;&amp; page.id != portal.login_page_dv &amp;&amp; !data.hasLogin)" class="nav navbar-nav" role="presentation"&gt;
        &lt;li role="presentation"&gt;&lt;a href ng-click="::openLogin()"&gt;${Login}&lt;/a&gt;&lt;/li&gt;
      &lt;/ul&gt;
      &lt;ul ng-if="user.logged_in" class="nav navbar-nav" role="menubar"&gt;
        &lt;!-- chat, avatar, and logout --&gt;
        &lt;li ng-if="::(data.connect_support_queue_id &amp;&amp; !isAgentChatConfigured)" role="presentation"&gt;&lt;a href ng-click="openPopUp()" role="menuitem"&gt;${Live Chat}&lt;/a&gt;&lt;/li&gt;
        &lt;li ng-if="showAvatar" class="hidden-xs hidden-sm dropdown" role="presentation"&gt;
          &lt;a href class="toggle-dropdown" data-toggle="dropdown" aria-expanded="false" aria-label="{{::data.profileBtnMsg}}: {{::user.name}}" id="profile-dropdown"  role="menuitem" aria-haspopup="true"&gt;
            &lt;span class="navbar-avatar" aria-hidden="true"&gt;&lt;sn-avatar class="avatar-small-medium" primary="avatarProfile" /&gt;&lt;/span&gt;
            &lt;span class="visible-lg-inline"&gt;{{::user.name}}&lt;/span&gt;
          &lt;/a&gt;
          &lt;ul class="dropdown-menu" role="menu" aria-label="{{::data.profileBtnMsg}}"&gt;
            &lt;li role="presentation"&gt;&lt;a tabindex="-1" ng-href="?id=user_profile&amp;sys_id={{::user.sys_id}}" role="menuitem"&gt;${Profile}&lt;/a&gt;&lt;/li&gt;
            &lt;li ng-if="::!(isViewNative || isViewNativeTablet)" role="presentation"&gt;&lt;a tabindex="-1" href="{{::portal.logoutUrl}}" role="menuitem"&gt;${Logout}&lt;/a&gt;&lt;/li&gt;
          &lt;/ul&gt;
        &lt;/li&gt;
        &lt;li ng-if="showSMAvatar" class="visible-xs-block visible-sm-block" role="presentation"&gt;&lt;a role="menuitem" ng-href="?id=user_profile&amp;sys_id={{::user.sys_id}}" ng-click="collapse()"&gt;
          &lt;span class="navbar-avatar"&gt;&lt;sn-avatar class="avatar-small-medium" primary="avatarProfile" /&gt;&lt;/span&gt;{{::user.name}}&lt;/a&gt;
        &lt;/li&gt;
        &lt;li ng-if="::!(isViewNative || isViewNativeTablet)" class="visible-xs-block visible-sm-block" role="presentation"&gt;&lt;a role="menuitem" ng-href="{{::portal.logoutUrl}}" ng-click="collapse()"&gt;${Logout}&lt;/a&gt;&lt;/li&gt;
      &lt;/ul&gt;
    &lt;/div&gt;
  &lt;/nav&gt;
&lt;/div&gt;]]&gt;&lt;/template&gt;&lt;/sp_header_footer&gt;&lt;/record_update&gt;</payload>
        <payload_hash>2119740605</payload_hash>
        <record_name>Auctionarc_header</record_name>
        <reverted_from/>
        <source>8ecdfa001baae1109cb1639bbc4bcb84</source>
        <source_table>sys_update_set</source_table>
        <state>previous</state>
        <sys_created_by>CC-Harsha</sys_created_by>
        <sys_created_on>2023-05-11 09:26:45</sys_created_on>
        <sys_id>a7a0dba81bfae1109cb1639bbc4bcbb6</sys_id>
        <sys_mod_count>0</sys_mod_count>
        <sys_recorded_at>1880a22621d0000001</sys_recorded_at>
        <sys_updated_by>CC-Harsha</sys_updated_by>
        <sys_updated_on>2023-05-11 09:26:45</sys_updated_on>
        <type>Header | Footer</type>
        <update_guid>afa0dba87ffae110297d81c7b96a86b5</update_guid>
        <update_guid_history>afa0dba87ffae110297d81c7b96a86b5:2119740605,43c7cb6072fae1101ad81021e3c169ed:1496377782,5c174b2049fae1106ac9df9d2114f18b:-354522368,21964fac9bbae110cd47dc66e7ad3f14:-3125214,17fc5ea4563ae110cd9b8b14d40cbee1:471651702,fc3c9ea4813ae110cc576892856c6865:-288242651,dd0c9ea4363ae1107ef734ac2677f660:1012764099,12ca5ea4743ae11037e57dbcbefb6a26:16800096,cfd25484d736611019d93adc446189c9:-1988784106,eec25484a8366110ee95f9b4a2f8b1c4:-591711219,fab258440a3661106cee3d862d0f955d:-1988784106,94529c4445366110003fb55ac8bdfdb7:95183906,3222584491366110eee58974c9cab84b:437089484,71d1d804563661108281923ea357ff38:1254897149</update_guid_history>
    </sys_update_version>
    <sys_metadata_delete action="INSERT_OR_UPDATE">
        <sys_audit_delete display_value="Auctionarc_header">8a4367b0977221102d93fcd0f053afbc</sys_audit_delete>
        <sys_class_name>sys_metadata_delete</sys_class_name>
        <sys_created_by>CC-Harsha</sys_created_by>
        <sys_created_on>2023-05-12 05:26:29</sys_created_on>
        <sys_db_object display_value="" name="sp_header_footer">sp_header_footer</sys_db_object>
        <sys_id>23983907edf0457099cf83f622569f84</sys_id>
        <sys_metadata>3dd1d8041b3661109cb1639bbc4bcb36</sys_metadata>
        <sys_mod_count>0</sys_mod_count>
        <sys_name>Auctionarc_header</sys_name>
        <sys_package display_value="AuctionArc" source="x_1046400_auction">6e876ac81b2ae1109cb1639bbc4bcb2b</sys_package>
        <sys_parent/>
        <sys_policy/>
        <sys_scope display_value="AuctionArc">6e876ac81b2ae1109cb1639bbc4bcb2b</sys_scope>
        <sys_scope_delete display_value="">10c6971d357c4e70bbe797ff9cc0de90</sys_scope_delete>
        <sys_update_name>sp_header_footer_3dd1d8041b3661109cb1639bbc4bcb36</sys_update_name>
        <sys_update_version display_value="sp_header_footer_3dd1d8041b3661109cb1639bbc4bcb36">a7a0dba81bfae1109cb1639bbc4bcbb6</sys_update_version>
        <sys_updated_by>CC-Harsha</sys_updated_by>
        <sys_updated_on>2023-05-12 05:26:29</sys_updated_on>
    </sys_metadata_delete>
</record_update>
